download_torch_pkm_repo-0.1.0.dist-info/LICENSE
download_torch_pkm_repo-0.1.0.dist-info/WHEEL
download_torch_pkm_repo-0.1.0.dist-info/METADATA
download_torch_pkm_repo-0.1.0.dist-info/entry_points.txt
download_torch_pkm_repo/pkm_extension.py
download_torch_pkm_repo/torch_repository.py
download_torch_pkm_repo/__init__.py
download_torch_pkm_repo/cuda_compatibility.py
download_torch_pkm_repo/utils/html.py
download_torch_pkm_repo/utils/__init__.py
download_torch_pkm_repo/resources/cuda-compatibilities.toml
download_torch_pkm_repo/resources/__init__.py
